{
    "TVT 1": {
        "Day 1": {
            "Game 1": "Синие 2-5 (Мотопехота/2-4 Экипаж БМП-2)",
            "Game 2": "Синие 1-4 (Мотопехота/1-3 Экипаж Страйкер)"
        },
        "Day 2": {
            "Game 1": "Красные 2-1 (СПН/2-2 x1 Миномёт M120)",
            "Game 2": "Красные 2-1 (Пехота/Зушка+ПКМ)"
        }
    },
    "TVT 2": {
        "Day 1": {
            "Game 1": "Синие (Неизвестно)",
            "Game 2": "Синие (Неизвестно)"
        },
        "Day 2": {
            "Game 1": "Красные 2-5 (Мотопехота/2-4 Экипаж Марид)",
            "Game 2": "Синие 1-1 (КС/3-5 ФПВ/3-6 Пилоты+десант Мед)"
        }
    }
}